soft_music/__init__.py
soft_music/decorator_tools.py
soft_music/decrypt.py
soft_music/file_tools.py
soft_music/paser_tools.py
soft_music/redis_queue.py
soft_music/selenium_tools.py
soft_music/spider_tools.py
soft_music/str_or_bytes_tools.py
soft_music/time_tools.py
soft_music-0.0.2.dist-info/METADATA
soft_music-0.0.2.dist-info/WHEEL
soft_music-0.0.2.dist-info/top_level.txt
soft_music-0.0.2.dist-info/RECORD
